License
MANIFEST.in
README.rst
example_usage
requirements.txt
setup.py
bin/dtw_synth
bin/get_mcd_dtw
bin/get_mcd_plain
bin/test_cli.py
mcd/__init__.py
mcd/dtw.py
mcd/metrics.py
mcd/metrics_fast.c
mcd/metrics_fast.pyx
mcd/test_dtw.py
mcd/test_metrics.py
mcd/util.py
mcd.egg-info/PKG-INFO
mcd.egg-info/SOURCES.txt
mcd.egg-info/dependency_links.txt
mcd.egg-info/requires.txt
mcd.egg-info/top_level.txt
test_data/corpus.lst
test_data/aligned-synth-examples/cmu_us_arctic_slt_a0003.bap
test_data/aligned-synth-examples/cmu_us_arctic_slt_a0003.lf0
test_data/aligned-synth-examples/cmu_us_arctic_slt_a0003.mgc
test_data/aligned-synth-examples/cmu_us_arctic_slt_a0044.bap
test_data/aligned-synth-examples/cmu_us_arctic_slt_a0044.lf0
test_data/aligned-synth-examples/cmu_us_arctic_slt_a0044.mgc
test_data/aligned-synth-examples/alignment/cmu_us_arctic_slt_a0003.lab
test_data/aligned-synth-examples/alignment/cmu_us_arctic_slt_a0044.lab
test_data/out-dtw_synth/cmu_us_arctic_slt_a0003.bap
test_data/out-dtw_synth/cmu_us_arctic_slt_a0003.lf0
test_data/out-dtw_synth/cmu_us_arctic_slt_a0003.mgc
test_data/out-dtw_synth/cmu_us_arctic_slt_a0044.bap
test_data/out-dtw_synth/cmu_us_arctic_slt_a0044.lf0
test_data/out-dtw_synth/cmu_us_arctic_slt_a0044.mgc
test_data/ref-examples/cmu_us_arctic_slt_a0003.mgc
test_data/ref-examples/cmu_us_arctic_slt_a0044.mgc
test_data/synth-examples/cmu_us_arctic_slt_a0003.bap
test_data/synth-examples/cmu_us_arctic_slt_a0003.lf0
test_data/synth-examples/cmu_us_arctic_slt_a0003.mgc
test_data/synth-examples/cmu_us_arctic_slt_a0044.bap
test_data/synth-examples/cmu_us_arctic_slt_a0044.lf0
test_data/synth-examples/cmu_us_arctic_slt_a0044.mgc