Metadata-Version: 1.0
Name: mcd
Version: 0.4
Summary: Mel cepstral distortion (MCD) computations in python.
Home-page: http://github.com/MattShannon/mcd
Author: Matt Shannon
Author-email: matt.shannon@cantab.net
License: 3-clause BSD (see License file)
Platform: UNKNOWN
